quantportfolio/__init__.py
quantportfolio/data.py
quantportfolio/optimizer.py
quantportfolio/performance.py
quantportfolio-0.0.3.dist-info/METADATA
quantportfolio-0.0.3.dist-info/WHEEL
quantportfolio-0.0.3.dist-info/licenses/License
quantportfolio-0.0.3.dist-info/RECORD
