Metadata-Version: 2.4
Name: quantportfolio
Version: 0.0.3
Summary: A toolkit for portfolio optimization
Project-URL: Homepage, https://github.com/chongjunli/quantportfolio
Project-URL: Issues, https://github.com/chongjunli/quantportfolio/issues
Author-email: Chongjun Li <cho.li@outlook.com>
License-Expression: MIT
License-File: License
Classifier: Operating System :: OS Independent
Classifier: Programming Language :: Python :: 3
Requires-Python: >=3.9
